{"format":2,"version":"5.1","globals":"89d3d7a6c2fdd02cac003c9c10c9af19","files":{"openseries___init___py":{"hash":"af9d0d0de0ea3b71d198bc63f1499a7d","index":{"nums":[1,0,0,0,0,0,0],"html_filename":"openseries___init___py.html","relative_filename":"openseries\\__init__.py"}},"openseries_captor_open_api_sdk_py":{"hash":"dbd40efa31ff0b19a3bd540e184f5e94","index":{"nums":[1,35,0,4,0,0,0],"html_filename":"openseries_captor_open_api_sdk_py.html","relative_filename":"openseries\\captor_open_api_sdk.py"}},"openseries_datefixer_py":{"hash":"5f0c457bed38f2621343bfd615540a6a","index":{"nums":[1,36,0,3,0,0,0],"html_filename":"openseries_datefixer_py.html","relative_filename":"openseries\\datefixer.py"}},"openseries_frame_py":{"hash":"949f97018881df0bb8ed3ff44a44d48d","index":{"nums":[1,555,0,85,0,0,0],"html_filename":"openseries_frame_py.html","relative_filename":"openseries\\frame.py"}},"openseries_load_plotly_py":{"hash":"edb7ef44d4a6f4dd93120da148b67690","index":{"nums":[1,11,0,0,0,0,0],"html_filename":"openseries_load_plotly_py.html","relative_filename":"openseries\\load_plotly.py"}},"openseries_risk_py":{"hash":"66d43612c828aae76c4b2e89397b18d9","index":{"nums":[1,42,0,1,0,0,0],"html_filename":"openseries_risk_py.html","relative_filename":"openseries\\risk.py"}},"openseries_series_py":{"hash":"8748dc7b690913059365416b50a7a18a","index":{"nums":[1,482,0,35,0,0,0],"html_filename":"openseries_series_py.html","relative_filename":"openseries\\series.py"}},"openseries_sim_price_py":{"hash":"07cffd88282d4e0c273f5c24277888d4","index":{"nums":[1,85,0,3,0,0,0],"html_filename":"openseries_sim_price_py.html","relative_filename":"openseries\\sim_price.py"}},"openseries_stoch_processes_py":{"hash":"d550b5d6c321cb5117c702601c5d5eab","index":{"nums":[1,145,0,18,0,0,0],"html_filename":"openseries_stoch_processes_py.html","relative_filename":"openseries\\stoch_processes.py"}},"openseries_sweden_holidays_py":{"hash":"f129b376443e78abd0f8ac47d84c5c6f","index":{"nums":[1,6,0,0,0,0,0],"html_filename":"openseries_sweden_holidays_py.html","relative_filename":"openseries\\sweden_holidays.py"}}}}